blender_remote/README.md
blender_remote/__init__.py
blender_remote/asset_manager.py
blender_remote/cli.py
blender_remote/client.py
blender_remote/data_types.py
blender_remote/exceptions.py
blender_remote/mcp_server.py
blender_remote/scene_manager.py
blender_remote/addon/bld_remote_mcp/__init__.py
blender_remote/addon/bld_remote_mcp/config.py
blender_remote/addon/bld_remote_mcp/persist.py
blender_remote/addon/bld_remote_mcp/utils.py
blender_remote/addon/simple-tcp-executor/__init__.py
blender_remote/addon/simple-tcp-executor/as_modal_operator.py
blender_remote-1.2.8.dist-info/licenses/LICENSE
blender_remote-1.2.8.dist-info/METADATA
blender_remote-1.2.8.dist-info/WHEEL
blender_remote-1.2.8.dist-info/entry_points.txt
blender_remote-1.2.8.dist-info/top_level.txt
blender_remote-1.2.8.dist-info/RECORD
