Metadata-Version: 2.4
Name: blender-remote
Version: 1.2.8
Summary: Automate Blender workflows with external Python control, background operation, and LLM integration
Author: blender-remote contributors
Maintainer: blender-remote contributors
License: MIT
Project-URL: Homepage, https://github.com/igamenovoer/blender-remote
Project-URL: Documentation, https://igamenovoer.github.io/blender-remote/
Project-URL: Repository, https://github.com/igamenovoer/blender-remote.git
Project-URL: Bug Tracker, https://github.com/igamenovoer/blender-remote/issues
Keywords: blender,remote-control,3d,automation,mcp,api
Classifier: Development Status :: 3 - Alpha
Classifier: Intended Audience :: Developers
Classifier: Topic :: Multimedia :: Graphics :: 3D Modeling
Classifier: Topic :: Software Development :: Libraries :: Python Modules
Classifier: License :: OSI Approved :: MIT License
Classifier: Programming Language :: Python :: 3
Classifier: Programming Language :: Python :: 3.11
Classifier: Programming Language :: Python :: 3.12
Requires-Python: >=3.11
License-File: LICENSE
Requires-Dist: fastmcp>=2.0.0
Requires-Dist: click>=8.0.0
Requires-Dist: pydantic>=2.11.7
Requires-Dist: omegaconf>=2.3.0
Requires-Dist: platformdirs
Requires-Dist: attrs>=25.3.0
Requires-Dist: numpy>=1.24.0
Requires-Dist: scipy>=1.16.0
Requires-Dist: trimesh>=3.0.0
Requires-Dist: requests>=2.32.4
Requires-Dist: uvicorn>=0.35.0
Requires-Dist: importlib_resources>=1.3.0
Provides-Extra: dev
Requires-Dist: pytest>=7.0.0; extra == "dev"
Requires-Dist: pytest-cov>=4.0.0; extra == "dev"
Requires-Dist: black>=22.0.0; extra == "dev"
Requires-Dist: ruff>=0.1.0; extra == "dev"
Requires-Dist: mypy>=1.0.0; extra == "dev"
Requires-Dist: pre-commit>=3.0.0; extra == "dev"
Provides-Extra: docs
Requires-Dist: mkdocs>=1.5.0; extra == "docs"
Requires-Dist: mkdocs-material>=9.0.0; extra == "docs"
Dynamic: license-file
